{"nodes": [{"id": "calculations", "label": "calculations.ts", "file_type": "code", "source_file": "src/features/cards/lib/calculations.ts", "source_location": "L1"}, {"id": "calculations_resolveunitvalue", "label": "resolveUnitValue()", "file_type": "code", "source_file": "src/features/cards/lib/calculations.ts", "source_location": "L89"}, {"id": "calculations_filtertoactiveperiod", "label": "filterToActivePeriod()", "file_type": "code", "source_file": "src/features/cards/lib/calculations.ts", "source_location": "L100"}, {"id": "calculations_gettotalvalueextracted", "label": "getTotalValueExtracted()", "file_type": "code", "source_file": "src/features/cards/lib/calculations.ts", "source_location": "L124"}, {"id": "calculations_getuncapturedvalue", "label": "getUncapturedValue()", "file_type": "code", "source_file": "src/features/cards/lib/calculations.ts", "source_location": "L154"}, {"id": "calculations_getnetannualfee", "label": "getNetAnnualFee()", "file_type": "code", "source_file": "src/features/cards/lib/calculations.ts", "source_location": "L183"}, {"id": "calculations_geteffectiveroi", "label": "getEffectiveROI()", "file_type": "code", "source_file": "src/features/cards/lib/calculations.ts", "source_location": "L221"}, {"id": "calculations_getexpirationwarnings", "label": "getExpirationWarnings()", "file_type": "code", "source_file": "src/features/cards/lib/calculations.ts", "source_location": "L241"}, {"id": "calculations_gethouseholdroi", "label": "getHouseholdROI()", "file_type": "code", "source_file": "src/features/cards/lib/calculations.ts", "source_location": "L304"}, {"id": "calculations_gethouseholdtotalcaptured", "label": "getHouseholdTotalCaptured()", "file_type": "code", "source_file": "src/features/cards/lib/calculations.ts", "source_location": "L349"}, {"id": "calculations_gethouseholdactivecount", "label": "getHouseholdActiveCount()", "file_type": "code", "source_file": "src/features/cards/lib/calculations.ts", "source_location": "L393"}, {"id": "calculations_geteffectiveannualfee", "label": "getEffectiveAnnualFee()", "file_type": "code", "source_file": "src/features/cards/lib/calculations.ts", "source_location": "L465"}, {"id": "calculations_getdaysuntilrenewal", "label": "getDaysUntilRenewal()", "file_type": "code", "source_file": "src/features/cards/lib/calculations.ts", "source_location": "L479"}, {"id": "calculations_getrenewalstatus", "label": "getRenewalStatus()", "file_type": "code", "source_file": "src/features/cards/lib/calculations.ts", "source_location": "L497"}, {"id": "calculations_formatrenewalcountdown", "label": "formatRenewalCountdown()", "file_type": "code", "source_file": "src/features/cards/lib/calculations.ts", "source_location": "L517"}, {"id": "calculations_getrenewalstatuscolor", "label": "getRenewalStatusColor()", "file_type": "code", "source_file": "src/features/cards/lib/calculations.ts", "source_location": "L542"}, {"id": "calculations_getstatusbadgecolor", "label": "getStatusBadgeColor()", "file_type": "code", "source_file": "src/features/cards/lib/calculations.ts", "source_location": "L566"}, {"id": "calculations_getstatuslabel", "label": "getStatusLabel()", "file_type": "code", "source_file": "src/features/cards/lib/calculations.ts", "source_location": "L589"}, {"id": "calculations_calculatecardroi", "label": "calculateCardROI()", "file_type": "code", "source_file": "src/features/cards/lib/calculations.ts", "source_location": "L615"}, {"id": "calculations_calculatewalletroi", "label": "calculateWalletROI()", "file_type": "code", "source_file": "src/features/cards/lib/calculations.ts", "source_location": "L636"}, {"id": "calculations_formatcurrency", "label": "formatCurrency()", "file_type": "code", "source_file": "src/features/cards/lib/calculations.ts", "source_location": "L652"}, {"id": "calculations_formatpercentage", "label": "formatPercentage()", "file_type": "code", "source_file": "src/features/cards/lib/calculations.ts", "source_location": "L669"}, {"id": "calculations_calculatebenefitssummary", "label": "calculateBenefitsSummary()", "file_type": "code", "source_file": "src/features/cards/lib/calculations.ts", "source_location": "L679"}, {"id": "calculations_cardcontributestoroi", "label": "cardContributesToROI()", "file_type": "code", "source_file": "src/features/cards/lib/calculations.ts", "source_location": "L733"}, {"id": "calculations_getrenewalstatustooltip", "label": "getRenewalStatusTooltip()", "file_type": "code", "source_file": "src/features/cards/lib/calculations.ts", "source_location": "L745"}, {"id": "calculations_calculatearchiveroiimpact", "label": "calculateArchiveROIImpact()", "file_type": "code", "source_file": "src/features/cards/lib/calculations.ts", "source_location": "L776"}], "edges": [{"source": "calculations", "target": "client", "relation": "imports_from", "confidence": "EXTRACTED", "source_file": "src/features/cards/lib/calculations.ts", "source_location": "L12", "weight": 1.0}, {"source": "calculations", "target": "types", "relation": "imports_from", "confidence": "EXTRACTED", "source_file": "src/features/cards/lib/calculations.ts", "source_location": "L13", "weight": 1.0}, {"source": "calculations", "target": "feature_flags", "relation": "imports_from", "confidence": "EXTRACTED", "source_file": "src/features/cards/lib/calculations.ts", "source_location": "L14", "weight": 1.0}, {"source": "calculations", "target": "calculations_resolveunitvalue", "relation": "contains", "confidence": "EXTRACTED", "source_file": "src/features/cards/lib/calculations.ts", "source_location": "L89", "weight": 1.0}, {"source": "calculations", "target": "calculations_filtertoactiveperiod", "relation": "contains", "confidence": "EXTRACTED", "source_file": "src/features/cards/lib/calculations.ts", "source_location": "L100", "weight": 1.0}, {"source": "calculations", "target": "calculations_gettotalvalueextracted", "relation": "contains", "confidence": "EXTRACTED", "source_file": "src/features/cards/lib/calculations.ts", "source_location": "L124", "weight": 1.0}, {"source": "calculations", "target": "calculations_getuncapturedvalue", "relation": "contains", "confidence": "EXTRACTED", "source_file": "src/features/cards/lib/calculations.ts", "source_location": "L154", "weight": 1.0}, {"source": "calculations", "target": "calculations_getnetannualfee", "relation": "contains", "confidence": "EXTRACTED", "source_file": "src/features/cards/lib/calculations.ts", "source_location": "L183", "weight": 1.0}, {"source": "calculations", "target": "calculations_geteffectiveroi", "relation": "contains", "confidence": "EXTRACTED", "source_file": "src/features/cards/lib/calculations.ts", "source_location": "L221", "weight": 1.0}, {"source": "calculations", "target": "calculations_getexpirationwarnings", "relation": "contains", "confidence": "EXTRACTED", "source_file": "src/features/cards/lib/calculations.ts", "source_location": "L241", "weight": 1.0}, {"source": "calculations", "target": "calculations_gethouseholdroi", "relation": "contains", "confidence": "EXTRACTED", "source_file": "src/features/cards/lib/calculations.ts", "source_location": "L304", "weight": 1.0}, {"source": "calculations", "target": "calculations_gethouseholdtotalcaptured", "relation": "contains", "confidence": "EXTRACTED", "source_file": "src/features/cards/lib/calculations.ts", "source_location": "L349", "weight": 1.0}, {"source": "calculations", "target": "calculations_gethouseholdactivecount", "relation": "contains", "confidence": "EXTRACTED", "source_file": "src/features/cards/lib/calculations.ts", "source_location": "L393", "weight": 1.0}, {"source": "calculations", "target": "calculations_geteffectiveannualfee", "relation": "contains", "confidence": "EXTRACTED", "source_file": "src/features/cards/lib/calculations.ts", "source_location": "L465", "weight": 1.0}, {"source": "calculations", "target": "calculations_getdaysuntilrenewal", "relation": "contains", "confidence": "EXTRACTED", "source_file": "src/features/cards/lib/calculations.ts", "source_location": "L479", "weight": 1.0}, {"source": "calculations", "target": "calculations_getrenewalstatus", "relation": "contains", "confidence": "EXTRACTED", "source_file": "src/features/cards/lib/calculations.ts", "source_location": "L497", "weight": 1.0}, {"source": "calculations", "target": "calculations_formatrenewalcountdown", "relation": "contains", "confidence": "EXTRACTED", "source_file": "src/features/cards/lib/calculations.ts", "source_location": "L517", "weight": 1.0}, {"source": "calculations", "target": "calculations_getrenewalstatuscolor", "relation": "contains", "confidence": "EXTRACTED", "source_file": "src/features/cards/lib/calculations.ts", "source_location": "L542", "weight": 1.0}, {"source": "calculations", "target": "calculations_getstatusbadgecolor", "relation": "contains", "confidence": "EXTRACTED", "source_file": "src/features/cards/lib/calculations.ts", "source_location": "L566", "weight": 1.0}, {"source": "calculations", "target": "calculations_getstatuslabel", "relation": "contains", "confidence": "EXTRACTED", "source_file": "src/features/cards/lib/calculations.ts", "source_location": "L589", "weight": 1.0}, {"source": "calculations", "target": "calculations_calculatecardroi", "relation": "contains", "confidence": "EXTRACTED", "source_file": "src/features/cards/lib/calculations.ts", "source_location": "L615", "weight": 1.0}, {"source": "calculations", "target": "calculations_calculatewalletroi", "relation": "contains", "confidence": "EXTRACTED", "source_file": "src/features/cards/lib/calculations.ts", "source_location": "L636", "weight": 1.0}, {"source": "calculations", "target": "calculations_formatcurrency", "relation": "contains", "confidence": "EXTRACTED", "source_file": "src/features/cards/lib/calculations.ts", "source_location": "L652", "weight": 1.0}, {"source": "calculations", "target": "calculations_formatpercentage", "relation": "contains", "confidence": "EXTRACTED", "source_file": "src/features/cards/lib/calculations.ts", "source_location": "L669", "weight": 1.0}, {"source": "calculations", "target": "calculations_calculatebenefitssummary", "relation": "contains", "confidence": "EXTRACTED", "source_file": "src/features/cards/lib/calculations.ts", "source_location": "L679", "weight": 1.0}, {"source": "calculations", "target": "calculations_cardcontributestoroi", "relation": "contains", "confidence": "EXTRACTED", "source_file": "src/features/cards/lib/calculations.ts", "source_location": "L733", "weight": 1.0}, {"source": "calculations", "target": "calculations_getrenewalstatustooltip", "relation": "contains", "confidence": "EXTRACTED", "source_file": "src/features/cards/lib/calculations.ts", "source_location": "L745", "weight": 1.0}, {"source": "calculations", "target": "calculations_calculatearchiveroiimpact", "relation": "contains", "confidence": "EXTRACTED", "source_file": "src/features/cards/lib/calculations.ts", "source_location": "L776", "weight": 1.0}, {"source": "calculations_gettotalvalueextracted", "target": "calculations_filtertoactiveperiod", "relation": "calls", "confidence": "EXTRACTED", "source_file": "src/features/cards/lib/calculations.ts", "source_location": "L126", "weight": 1.0}, {"source": "calculations_getuncapturedvalue", "target": "calculations_filtertoactiveperiod", "relation": "calls", "confidence": "EXTRACTED", "source_file": "src/features/cards/lib/calculations.ts", "source_location": "L157", "weight": 1.0}, {"source": "calculations_getnetannualfee", "target": "calculations_filtertoactiveperiod", "relation": "calls", "confidence": "EXTRACTED", "source_file": "src/features/cards/lib/calculations.ts", "source_location": "L197", "weight": 1.0}, {"source": "calculations_geteffectiveroi", "target": "calculations_gettotalvalueextracted", "relation": "calls", "confidence": "EXTRACTED", "source_file": "src/features/cards/lib/calculations.ts", "source_location": "L226", "weight": 1.0}, {"source": "calculations_geteffectiveroi", "target": "calculations_getnetannualfee", "relation": "calls", "confidence": "EXTRACTED", "source_file": "src/features/cards/lib/calculations.ts", "source_location": "L227", "weight": 1.0}, {"source": "calculations_getexpirationwarnings", "target": "calculations_filtertoactiveperiod", "relation": "calls", "confidence": "EXTRACTED", "source_file": "src/features/cards/lib/calculations.ts", "source_location": "L249", "weight": 1.0}]}